{
  "sections": [
    {
      "title": "{{username}}@github",
      "fields": [
        { "key": "Name", "value": "Simon Fung" },
        { "key": "Education", "value": "B.Eng. SEEM & CS @ CUHK" },
        { "key": "Certifications", "value": "OSCP, OSCP+, OSWP" },
        { "key": "Focus", "value": "Penetration Testing & Red Teaming" }
      ]
    },
    {
      "title": "- Skills & Arsenal",
      "fields": [
        {
          "key": "Offensive Sec",
          "value": "Metasploit, Aircrack-ng, AD Attacks, Kali"
        },
        { "key": "Dev & Data", "value": "Python, React, SQL, C/C++" }
      ]
    },
    {
      "title": "- Connect",
      "fields": [
        { "key": "Portfolio", "value": "https://skiraware.github.io/" },
        { "key": "LinkedIn", "value": "linkedin.com/in/fungsaiwa" },
        { "key": "Email", "value": "simonfung@link.cuhk.edu.hk" }
      ]
    }
  ],
  "stats": {
    "title": "- GitHub Stats",
    "rows": [
      {
        "left": { "key": "Repos", "value": "{{repos}}" },
        "right": { "key": "Stars", "value": "{{stars}}" }
      },
      {
        "left": { "key": "Commits", "value": "{{commits}}" },
        "right": { "key": "Followers", "value": "{{followers}}" }
      },
      "loc"
    ]
  }
}
